{
  "nodes": [
    {
      "id": "シゴトモエール",
      "name": "シゴトモエール"
    },
    {
      "id": "/",
      "name": "/"
    },
    {
      "id": "/zenkoku/SC16",
      "name": "/zenkoku/SC16"
    },
    {
      "id": "/zenkoku/PC15",
      "name": "/zenkoku/PC15"
    },
    {
      "id": "/zenkoku/MC1",
      "name": "/zenkoku/MC1"
    },
    {
      "id": "/zenkoku/PC27",
      "name": "/zenkoku/PC27"
    },
    {
      "id": "/zenkoku/DC28201",
      "name": "/zenkoku/DC28201"
    },
    {
      "id": "/kyujin/535",
      "name": "/kyujin/535"
    },
    {
      "id": "/zenkoku/DC27207",
      "name": "/zenkoku/DC27207"
    },
    {
      "id": "/kyujin/16258",
      "name": "/kyujin/16258"
    },
    {
      "id": "/kyujin/15477",
      "name": "/kyujin/15477"
    },
    {
      "id": "/kyujin/2275",
      "name": "/kyujin/2275"
    },
    {
      "id": "/zenkoku/PC28",
      "name": "/zenkoku/PC28"
    },
    {
      "id": "/zenkoku/DC27202",
      "name": "/zenkoku/DC27202"
    },
    {
      "id": "/zenkoku/DC28228",
      "name": "/zenkoku/DC28228"
    },
    {
      "id": "/zenkoku/PC15/MB1,2",
      "name": "/zenkoku/PC15/MB1,2"
    },
    {
      "id": "/zenkoku/PC27,28,26,29,25,30",
      "name": "/zenkoku/PC27,28,26,29,25,30"
    },
    {
      "id": "/zenkoku/DC27207,27211",
      "name": "/zenkoku/DC27207,27211"
    },
    {
      "id": "/zenkoku/SC18",
      "name": "/zenkoku/SC18"
    },
    {
      "id": "/zenkoku/DC28220",
      "name": "/zenkoku/DC28220"
    },
    {
      "id": "/zenkoku/PM61",
      "name": "/zenkoku/PM61"
    },
    {
      "id": "/zenkoku/DC15222",
      "name": "/zenkoku/DC15222"
    },
    {
      "id": "/zenkoku/DC27211",
      "name": "/zenkoku/DC27211"
    },
    {
      "id": "/zenkoku/DC27221",
      "name": "/zenkoku/DC27221"
    },
    {
      "id": "/zenkoku/DC28202",
      "name": "/zenkoku/DC28202"
    },
    {
      "id": "/apply/535",
      "name": "/apply/535"
    },
    {
      "id": "/kyujin/search-detail",
      "name": "/kyujin/search-detail"
    },
    {
      "id": "/zenkoku/DC25201,25204,25206,25207,25208,25210",
      "name": "/zenkoku/DC25201,25204,25206,25207,25208,25210"
    },
    {
      "id": "/zenkoku/PM151",
      "name": "/zenkoku/PM151"
    },
    {
      "id": "/zenkoku/SC21",
      "name": "/zenkoku/SC21"
    },
    {
      "id": "/keep",
      "name": "/keep"
    },
    {
      "id": "/zenkoku/DC15211",
      "name": "/zenkoku/DC15211"
    },
    {
      "id": "/zenkoku/DC27215",
      "name": "/zenkoku/DC27215"
    },
    {
      "id": "/zenkoku/PC10,9,8,13,14,12,11",
      "name": "/zenkoku/PC10,9,8,13,14,12,11"
    },
    {
      "id": "/zenkoku/PM98",
      "name": "/zenkoku/PM98"
    },
    {
      "id": "/zenkoku/SC2",
      "name": "/zenkoku/SC2"
    },
    {
      "id": "/zenkoku/SC8",
      "name": "/zenkoku/SC8"
    },
    {
      "id": "/zenkoku/DC15202",
      "name": "/zenkoku/DC15202"
    },
    {
      "id": "/zenkoku/DC26201,26203",
      "name": "/zenkoku/DC26201,26203"
    },
    {
      "id": "/zenkoku/DC27146",
      "name": "/zenkoku/DC27146"
    },
    {
      "id": "/zenkoku/PC27/MB1,2",
      "name": "/zenkoku/PC27/MB1,2"
    },
    {
      "id": "/zenkoku/PC28/MB1,2",
      "name": "/zenkoku/PC28/MB1,2"
    },
    {
      "id": "/zenkoku/PM100",
      "name": "/zenkoku/PM100"
    },
    {
      "id": "/zenkoku/PM467",
      "name": "/zenkoku/PM467"
    },
    {
      "id": "/zenkoku/SC17",
      "name": "/zenkoku/SC17"
    },
    {
      "id": "/zenkoku/SC19",
      "name": "/zenkoku/SC19"
    },
    {
      "id": "/zenkoku/search-result",
      "name": "/zenkoku/search-result"
    },
    {
      "id": "/zenkoku/DC28210",
      "name": "/zenkoku/DC28210"
    },
    {
      "id": "/zenkoku/DC27210",
      "name": "/zenkoku/DC27210"
    },
    {
      "id": "/zenkoku/DC28111",
      "name": "/zenkoku/DC28111"
    },
    {
      "id": "/zenkoku/PC25",
      "name": "/zenkoku/PC25"
    },
    {
      "id": "/zenkoku/DC24205",
      "name": "/zenkoku/DC24205"
    },
    {
      "id": "/zenkoku/PM152",
      "name": "/zenkoku/PM152"
    },
    {
      "id": "/zenkoku/PM156",
      "name": "/zenkoku/PM156"
    },
    {
      "id": "/zenkoku/DC28203",
      "name": "/zenkoku/DC28203"
    },
    {
      "id": "/zenkoku/DC25204",
      "name": "/zenkoku/DC25204"
    },
    {
      "id": "/zenkoku/DC25213",
      "name": "/zenkoku/DC25213"
    },
    {
      "id": "/zenkoku/PC24",
      "name": "/zenkoku/PC24"
    },
    {
      "id": "/zenkoku/PM148",
      "name": "/zenkoku/PM148"
    },
    {
      "id": "/zenkoku/DC25208",
      "name": "/zenkoku/DC25208"
    },
    {
      "id": "/zenkoku/DC28202,28207",
      "name": "/zenkoku/DC28202,28207"
    },
    {
      "id": "/zenkoku/DC26201",
      "name": "/zenkoku/DC26201"
    },
    {
      "id": "/zenkoku/PM159",
      "name": "/zenkoku/PM159"
    },
    {
      "id": "/zenkoku/DC27210,27230",
      "name": "/zenkoku/DC27210,27230"
    },
    {
      "id": "/zenkoku/PC14",
      "name": "/zenkoku/PC14"
    },
    {
      "id": "/zenkoku/PM150",
      "name": "/zenkoku/PM150"
    },
    {
      "id": "/zenkoku/PC11",
      "name": "/zenkoku/PC11"
    },
    {
      "id": "/zenkoku/PC10",
      "name": "/zenkoku/PC10"
    },
    {
      "id": "/zenkoku/DC24202",
      "name": "/zenkoku/DC24202"
    },
    {
      "id": "/zenkoku/DC27212",
      "name": "/zenkoku/DC27212"
    },
    {
      "id": "/zenkoku/DC28223",
      "name": "/zenkoku/DC28223"
    },
    {
      "id": "/zenkoku/PM91",
      "name": "/zenkoku/PM91"
    },
    {
      "id": "/zenkoku/PM92",
      "name": "/zenkoku/PM92"
    },
    {
      "id": "/zenkoku/DC28101",
      "name": "/zenkoku/DC28101"
    },
    {
      "id": "/zenkoku/DC28204",
      "name": "/zenkoku/DC28204"
    },
    {
      "id": "/zenkoku/DC28207",
      "name": "/zenkoku/DC28207"
    },
    {
      "id": "/zenkoku/DC28215",
      "name": "/zenkoku/DC28215"
    },
    {
      "id": "/zenkoku/TC1,2",
      "name": "/zenkoku/TC1,2"
    },
    {
      "id": "/zenkoku/DC28219",
      "name": "/zenkoku/DC28219"
    },
    {
      "id": "/zenkoku/PM130",
      "name": "/zenkoku/PM130"
    },
    {
      "id": "/zenkoku/DC25209",
      "name": "/zenkoku/DC25209"
    },
    {
      "id": "/zenkoku/DC28201,28229,28464",
      "name": "/zenkoku/DC28201,28229,28464"
    },
    {
      "id": "/zenkoku/SC27",
      "name": "/zenkoku/SC27"
    },
    {
      "id": "/zenkoku/DC21211",
      "name": "/zenkoku/DC21211"
    },
    {
      "id": "/zenkoku/PM158",
      "name": "/zenkoku/PM158"
    },
    {
      "id": "/zenkoku/DC15217,15222",
      "name": "/zenkoku/DC15217,15222"
    },
    {
      "id": "/zenkoku/DC25206,25207,25208,25210",
      "name": "/zenkoku/DC25206,25207,25208,25210"
    },
    {
      "id": "/zenkoku/PC23,21,24",
      "name": "/zenkoku/PC23,21,24"
    },
    {
      "id": "/zenkoku/DC15102",
      "name": "/zenkoku/DC15102"
    },
    {
      "id": "/zenkoku/DC15204",
      "name": "/zenkoku/DC15204"
    },
    {
      "id": "/zenkoku/PM91,92",
      "name": "/zenkoku/PM91,92"
    },
    {
      "id": "/zenkoku/DC28109",
      "name": "/zenkoku/DC28109"
    },
    {
      "id": "/zenkoku/DC28203,28210,28381,28382",
      "name": "/zenkoku/DC28203,28210,28381,28382"
    },
    {
      "id": "/zenkoku/DC27108",
      "name": "/zenkoku/DC27108"
    },
    {
      "id": "/zenkoku/DC28213",
      "name": "/zenkoku/DC28213"
    },
    {
      "id": "/zenkoku/PM50",
      "name": "/zenkoku/PM50"
    },
    {
      "id": "/zenkoku/DC27113",
      "name": "/zenkoku/DC27113"
    },
    {
      "id": "/zenkoku/PM137",
      "name": "/zenkoku/PM137"
    },
    {
      "id": "/apply/confirm",
      "name": "/apply/confirm"
    },
    {
      "id": "/apply/complete",
      "name": "/apply/complete"
    }
  ],
  "links": [
    {
      "source": "シゴトモエール",
      "target": "/",
      "value": 315,
      "tooltip": "シゴトモエール > /"
    },
    {
      "source": "シゴトモエール",
      "target": "/zenkoku/SC16",
      "value": 11,
      "tooltip": "シゴトモエール > /zenkoku/SC16"
    },
    {
      "source": "シゴトモエール",
      "target": "/zenkoku/PC15",
      "value": 11,
      "tooltip": "シゴトモエール > /zenkoku/PC15"
    },
    {
      "source": "シゴトモエール",
      "target": "/zenkoku/MC1",
      "value": 1,
      "tooltip": "シゴトモエール > /zenkoku/MC1"
    },
    {
      "source": "シゴトモエール",
      "target": "/zenkoku/PC27",
      "value": 1,
      "tooltip": "シゴトモエール > /zenkoku/PC27"
    },
    {
      "source": "シゴトモエール",
      "target": "/zenkoku/DC28201",
      "value": 1,
      "tooltip": "シゴトモエール > /zenkoku/DC28201"
    },
    {
      "source": "シゴトモエール",
      "target": "/kyujin/535",
      "value": 2,
      "tooltip": "シゴトモエール > /kyujin/535"
    },
    {
      "source": "シゴトモエール",
      "target": "/zenkoku/DC27207",
      "value": 1,
      "tooltip": "シゴトモエール > /zenkoku/DC27207"
    },
    {
      "source": "シゴトモエール",
      "target": "/kyujin/16258",
      "value": 1,
      "tooltip": "シゴトモエール > /kyujin/16258"
    },
    {
      "source": "シゴトモエール",
      "target": "/kyujin/15477",
      "value": 2,
      "tooltip": "シゴトモエール > /kyujin/15477"
    },
    {
      "source": "シゴトモエール",
      "target": "/kyujin/2275",
      "value": 1,
      "tooltip": "シゴトモエール > /kyujin/2275"
    },
    {
      "source": "シゴトモエール",
      "target": "/zenkoku/PC28",
      "value": 1,
      "tooltip": "シゴトモエール > /zenkoku/PC28"
    },
    {
      "source": "シゴトモエール",
      "target": "/zenkoku/DC27202",
      "value": 1,
      "tooltip": "シゴトモエール > /zenkoku/DC27202"
    },
    {
      "source": "/",
      "target": "/zenkoku/DC28228",
      "value": 1,
      "tooltip": "シゴトモエール > / > /zenkoku/DC28228"
    },
    {
      "source": "/",
      "target": "/zenkoku/PC15/MB1,2",
      "value": 2,
      "tooltip": "シゴトモエール > / > /zenkoku/PC15/MB1,2"
    },
    {
      "source": "/",
      "target": "/zenkoku/PC27,28,26,29,25,30",
      "value": 8,
      "tooltip": "シゴトモエール > / > /zenkoku/PC27,28,26,29,25,30"
    },
    {
      "source": "/",
      "target": "/zenkoku/DC27207,27211",
      "value": 1,
      "tooltip": "シゴトモエール > / > /zenkoku/DC27207,27211"
    },
    {
      "source": "/",
      "target": "/zenkoku/SC18",
      "value": 2,
      "tooltip": "シゴトモエール > / > /zenkoku/SC18"
    },
    {
      "source": "/",
      "target": "/zenkoku/DC28220",
      "value": 1,
      "tooltip": "シゴトモエール > / > /zenkoku/DC28220"
    },
    {
      "source": "/",
      "target": "/zenkoku/PM61",
      "value": 1,
      "tooltip": "シゴトモエール > / > /zenkoku/PM61"
    },
    {
      "source": "/",
      "target": "/zenkoku/SC16",
      "value": 7,
      "tooltip": "シゴトモエール > / > /zenkoku/SC16"
    },
    {
      "source": "/",
      "target": "/zenkoku/DC15222",
      "value": 1,
      "tooltip": "シゴトモエール > / > /zenkoku/DC15222"
    },
    {
      "source": "/",
      "target": "/zenkoku/DC27211",
      "value": 2,
      "tooltip": "シゴトモエール > / > /zenkoku/DC27211"
    },
    {
      "source": "/",
      "target": "/zenkoku/DC27221",
      "value": 1,
      "tooltip": "シゴトモエール > / > /zenkoku/DC27221"
    },
    {
      "source": "/",
      "target": "/zenkoku/DC28202",
      "value": 2,
      "tooltip": "シゴトモエール > / > /zenkoku/DC28202"
    },
    {
      "source": "/",
      "target": "/apply/535",
      "value": 4,
      "tooltip": "シゴトモエール > / > /apply/535"
    },
    {
      "source": "/",
      "target": "/kyujin/search-detail",
      "value": 6,
      "tooltip": "シゴトモエール > / > /kyujin/search-detail"
    },
    {
      "source": "/",
      "target": "/zenkoku/DC25201,25204,25206,25207,25208,25210",
      "value": 1,
      "tooltip": "シゴトモエール > / > /zenkoku/DC25201,25204,25206,25207,25208,25210"
    },
    {
      "source": "/",
      "target": "/zenkoku/DC28201",
      "value": 6,
      "tooltip": "シゴトモエール > / > /zenkoku/DC28201"
    },
    {
      "source": "/",
      "target": "/zenkoku/PM151",
      "value": 2,
      "tooltip": "シゴトモエール > / > /zenkoku/PM151"
    },
    {
      "source": "/",
      "target": "/zenkoku/SC21",
      "value": 3,
      "tooltip": "シゴトモエール > / > /zenkoku/SC21"
    },
    {
      "source": "/",
      "target": "/keep",
      "value": 8,
      "tooltip": "シゴトモエール > / > /keep"
    },
    {
      "source": "/",
      "target": "/zenkoku/DC15211",
      "value": 1,
      "tooltip": "シゴトモエール > / > /zenkoku/DC15211"
    },
    {
      "source": "/",
      "target": "/zenkoku/DC27215",
      "value": 1,
      "tooltip": "シゴトモエール > / > /zenkoku/DC27215"
    },
    {
      "source": "/",
      "target": "/zenkoku/PC10,9,8,13,14,12,11",
      "value": 4,
      "tooltip": "シゴトモエール > / > /zenkoku/PC10,9,8,13,14,12,11"
    },
    {
      "source": "/",
      "target": "/zenkoku/PM98",
      "value": 1,
      "tooltip": "シゴトモエール > / > /zenkoku/PM98"
    },
    {
      "source": "/",
      "target": "/zenkoku/SC2",
      "value": 2,
      "tooltip": "シゴトモエール > / > /zenkoku/SC2"
    },
    {
      "source": "/",
      "target": "/zenkoku/SC8",
      "value": 2,
      "tooltip": "シゴトモエール > / > /zenkoku/SC8"
    },
    {
      "source": "/",
      "target": "/zenkoku/DC15202",
      "value": 2,
      "tooltip": "シゴトモエール > / > /zenkoku/DC15202"
    },
    {
      "source": "/",
      "target": "/zenkoku/DC26201,26203",
      "value": 1,
      "tooltip": "シゴトモエール > / > /zenkoku/DC26201,26203"
    },
    {
      "source": "/",
      "target": "/zenkoku/DC27146",
      "value": 1,
      "tooltip": "シゴトモエール > / > /zenkoku/DC27146"
    },
    {
      "source": "/",
      "target": "/zenkoku/DC27207",
      "value": 2,
      "tooltip": "シゴトモエール > / > /zenkoku/DC27207"
    },
    {
      "source": "/",
      "target": "/zenkoku/PC27/MB1,2",
      "value": 1,
      "tooltip": "シゴトモエール > / > /zenkoku/PC27/MB1,2"
    },
    {
      "source": "/",
      "target": "/zenkoku/PC28/MB1,2",
      "value": 1,
      "tooltip": "シゴトモエール > / > /zenkoku/PC28/MB1,2"
    },
    {
      "source": "/",
      "target": "/zenkoku/PM100",
      "value": 1,
      "tooltip": "シゴトモエール > / > /zenkoku/PM100"
    },
    {
      "source": "/",
      "target": "/zenkoku/PM467",
      "value": 1,
      "tooltip": "シゴトモエール > / > /zenkoku/PM467"
    },
    {
      "source": "/",
      "target": "/zenkoku/SC17",
      "value": 2,
      "tooltip": "シゴトモエール > / > /zenkoku/SC17"
    },
    {
      "source": "/",
      "target": "/zenkoku/SC19",
      "value": 3,
      "tooltip": "シゴトモエール > / > /zenkoku/SC19"
    },
    {
      "source": "/",
      "target": "/zenkoku/search-result",
      "value": 2,
      "tooltip": "シゴトモエール > / > /zenkoku/search-result"
    },
    {
      "source": "/",
      "target": "/zenkoku/DC28210",
      "value": 1,
      "tooltip": "シゴトモエール > / > /zenkoku/DC28210"
    },
    {
      "source": "/",
      "target": "/zenkoku/DC27210",
      "value": 2,
      "tooltip": "シゴトモエール > / > /zenkoku/DC27210"
    },
    {
      "source": "/",
      "target": "/zenkoku/DC28111",
      "value": 1,
      "tooltip": "シゴトモエール > / > /zenkoku/DC28111"
    },
    {
      "source": "/",
      "target": "/zenkoku/PC25",
      "value": 1,
      "tooltip": "シゴトモエール > / > /zenkoku/PC25"
    },
    {
      "source": "/",
      "target": "/zenkoku/DC24205",
      "value": 1,
      "tooltip": "シゴトモエール > / > /zenkoku/DC24205"
    },
    {
      "source": "/",
      "target": "/zenkoku/PM152",
      "value": 1,
      "tooltip": "シゴトモエール > / > /zenkoku/PM152"
    },
    {
      "source": "/",
      "target": "/zenkoku/PM156",
      "value": 1,
      "tooltip": "シゴトモエール > / > /zenkoku/PM156"
    },
    {
      "source": "/",
      "target": "/zenkoku/DC28203",
      "value": 1,
      "tooltip": "シゴトモエール > / > /zenkoku/DC28203"
    },
    {
      "source": "/",
      "target": "/zenkoku/DC25204",
      "value": 1,
      "tooltip": "シゴトモエール > / > /zenkoku/DC25204"
    },
    {
      "source": "/",
      "target": "/zenkoku/DC25213",
      "value": 1,
      "tooltip": "シゴトモエール > / > /zenkoku/DC25213"
    },
    {
      "source": "/",
      "target": "/zenkoku/PC24",
      "value": 1,
      "tooltip": "シゴトモエール > / > /zenkoku/PC24"
    },
    {
      "source": "/",
      "target": "/zenkoku/PC27",
      "value": 1,
      "tooltip": "シゴトモエール > / > /zenkoku/PC27"
    },
    {
      "source": "/",
      "target": "/zenkoku/PC28",
      "value": 1,
      "tooltip": "シゴトモエール > / > /zenkoku/PC28"
    },
    {
      "source": "/",
      "target": "/zenkoku/PM148",
      "value": 2,
      "tooltip": "シゴトモエール > / > /zenkoku/PM148"
    },
    {
      "source": "/",
      "target": "/zenkoku/PC15",
      "value": 4,
      "tooltip": "シゴトモエール > / > /zenkoku/PC15"
    },
    {
      "source": "/",
      "target": "/zenkoku/DC25208",
      "value": 1,
      "tooltip": "シゴトモエール > / > /zenkoku/DC25208"
    },
    {
      "source": "/",
      "target": "/zenkoku/DC28202,28207",
      "value": 1,
      "tooltip": "シゴトモエール > / > /zenkoku/DC28202,28207"
    },
    {
      "source": "/",
      "target": "/zenkoku/DC26201",
      "value": 3,
      "tooltip": "シゴトモエール > / > /zenkoku/DC26201"
    },
    {
      "source": "/",
      "target": "/zenkoku/PM159",
      "value": 2,
      "tooltip": "シゴトモエール > / > /zenkoku/PM159"
    },
    {
      "source": "/",
      "target": "/zenkoku/DC27210,27230",
      "value": 1,
      "tooltip": "シゴトモエール > / > /zenkoku/DC27210,27230"
    },
    {
      "source": "/",
      "target": "/zenkoku/PC14",
      "value": 1,
      "tooltip": "シゴトモエール > / > /zenkoku/PC14"
    },
    {
      "source": "/",
      "target": "/zenkoku/PM150",
      "value": 3,
      "tooltip": "シゴトモエール > / > /zenkoku/PM150"
    },
    {
      "source": "/",
      "target": "/zenkoku/PC11",
      "value": 1,
      "tooltip": "シゴトモエール > / > /zenkoku/PC11"
    },
    {
      "source": "/",
      "target": "/zenkoku/PC10",
      "value": 1,
      "tooltip": "シゴトモエール > / > /zenkoku/PC10"
    },
    {
      "source": "/",
      "target": "/zenkoku/DC24202",
      "value": 1,
      "tooltip": "シゴトモエール > / > /zenkoku/DC24202"
    },
    {
      "source": "/",
      "target": "/zenkoku/DC27212",
      "value": 1,
      "tooltip": "シゴトモエール > / > /zenkoku/DC27212"
    },
    {
      "source": "/",
      "target": "/zenkoku/DC28223",
      "value": 1,
      "tooltip": "シゴトモエール > / > /zenkoku/DC28223"
    },
    {
      "source": "/",
      "target": "/zenkoku/PM91",
      "value": 1,
      "tooltip": "シゴトモエール > / > /zenkoku/PM91"
    },
    {
      "source": "/",
      "target": "/zenkoku/PM92",
      "value": 1,
      "tooltip": "シゴトモエール > / > /zenkoku/PM92"
    },
    {
      "source": "/",
      "target": "/zenkoku/DC28101",
      "value": 1,
      "tooltip": "シゴトモエール > / > /zenkoku/DC28101"
    },
    {
      "source": "/",
      "target": "/zenkoku/DC28204",
      "value": 1,
      "tooltip": "シゴトモエール > / > /zenkoku/DC28204"
    },
    {
      "source": "/",
      "target": "/zenkoku/DC28207",
      "value": 1,
      "tooltip": "シゴトモエール > / > /zenkoku/DC28207"
    },
    {
      "source": "/",
      "target": "/zenkoku/DC28215",
      "value": 1,
      "tooltip": "シゴトモエール > / > /zenkoku/DC28215"
    },
    {
      "source": "/",
      "target": "/zenkoku/TC1,2",
      "value": 1,
      "tooltip": "シゴトモエール > / > /zenkoku/TC1,2"
    },
    {
      "source": "/",
      "target": "/zenkoku/DC28219",
      "value": 1,
      "tooltip": "シゴトモエール > / > /zenkoku/DC28219"
    },
    {
      "source": "/",
      "target": "/zenkoku/PM130",
      "value": 1,
      "tooltip": "シゴトモエール > / > /zenkoku/PM130"
    },
    {
      "source": "/",
      "target": "/zenkoku/DC25209",
      "value": 1,
      "tooltip": "シゴトモエール > / > /zenkoku/DC25209"
    },
    {
      "source": "/",
      "target": "/zenkoku/DC28201,28229,28464",
      "value": 1,
      "tooltip": "シゴトモエール > / > /zenkoku/DC28201,28229,28464"
    },
    {
      "source": "/",
      "target": "/zenkoku/SC27",
      "value": 1,
      "tooltip": "シゴトモエール > / > /zenkoku/SC27"
    },
    {
      "source": "/",
      "target": "/zenkoku/DC21211",
      "value": 1,
      "tooltip": "シゴトモエール > / > /zenkoku/DC21211"
    },
    {
      "source": "/",
      "target": "/zenkoku/PM158",
      "value": 1,
      "tooltip": "シゴトモエール > / > /zenkoku/PM158"
    },
    {
      "source": "/",
      "target": "/zenkoku/DC15217,15222",
      "value": 1,
      "tooltip": "シゴトモエール > / > /zenkoku/DC15217,15222"
    },
    {
      "source": "/",
      "target": "/zenkoku/DC25206,25207,25208,25210",
      "value": 1,
      "tooltip": "シゴトモエール > / > /zenkoku/DC25206,25207,25208,25210"
    },
    {
      "source": "/",
      "target": "/zenkoku/PC23,21,24",
      "value": 1,
      "tooltip": "シゴトモエール > / > /zenkoku/PC23,21,24"
    },
    {
      "source": "/",
      "target": "/zenkoku/DC15102",
      "value": 1,
      "tooltip": "シゴトモエール > / > /zenkoku/DC15102"
    },
    {
      "source": "/",
      "target": "/zenkoku/DC15204",
      "value": 1,
      "tooltip": "シゴトモエール > / > /zenkoku/DC15204"
    },
    {
      "source": "/",
      "target": "/zenkoku/PM91,92",
      "value": 1,
      "tooltip": "シゴトモエール > / > /zenkoku/PM91,92"
    },
    {
      "source": "/",
      "target": "/zenkoku/DC28109",
      "value": 1,
      "tooltip": "シゴトモエール > / > /zenkoku/DC28109"
    },
    {
      "source": "/",
      "target": "/zenkoku/DC28203,28210,28381,28382",
      "value": 1,
      "tooltip": "シゴトモエール > / > /zenkoku/DC28203,28210,28381,28382"
    },
    {
      "source": "/",
      "target": "/zenkoku/DC27108",
      "value": 1,
      "tooltip": "シゴトモエール > / > /zenkoku/DC27108"
    },
    {
      "source": "/",
      "target": "/zenkoku/DC28213",
      "value": 1,
      "tooltip": "シゴトモエール > / > /zenkoku/DC28213"
    },
    {
      "source": "/",
      "target": "/zenkoku/PM50",
      "value": 1,
      "tooltip": "シゴトモエール > / > /zenkoku/PM50"
    },
    {
      "source": "/",
      "target": "/zenkoku/DC27113",
      "value": 1,
      "tooltip": "シゴトモエール > / > /zenkoku/DC27113"
    },
    {
      "source": "/",
      "target": "/zenkoku/PM137",
      "value": 1,
      "tooltip": "シゴトモエール > / > /zenkoku/PM137"
    },
    {
      "source": "/zenkoku/PC15",
      "target": "/kyujin/search-detail",
      "value": 1,
      "tooltip": "シゴトモエール > /zenkoku/PC15 > /kyujin/search-detail"
    },
    {
      "source": "/kyujin/535",
      "target": "/apply/535",
      "value": 1,
      "tooltip": "シゴトモエール > /kyujin/535 > /apply/535"
    },
    {
      "source": "/apply/535",
      "target": "/apply/confirm",
      "value": 3,
      "tooltip": "シゴトモエール > / > /apply/535 > /apply/confirm"
    },
    {
      "source": "/apply/535",
      "target": "/apply/confirm",
      "value": 1,
      "tooltip": "シゴトモエール > /kyujin/535 > /apply/535 > /apply/confirm"
    },
    {
      "source": "/apply/confirm",
      "target": "/apply/complete",
      "value": 3,
      "tooltip": "シゴトモエール > / > /apply/535 > /apply/confirm > /apply/complete"
    },
    {
      "source": "/apply/confirm",
      "target": "/apply/complete",
      "value": 1,
      "tooltip": "シゴトモエール > /kyujin/535 > /apply/535 > /apply/confirm > /apply/complete"
    }
  ]
}