{
  "nodes": [
    {
      "id": "会社見学 服装 女性",
      "name": "会社見学 服装 女性"
    },
    {
      "id": "https://www.shigotomo.jp/contents/articles/interview-clothes",
      "name": "https://www.shigotomo.jp/contents/articles/interview-clothes"
    },
    {
      "id": "https://www.shigotomo.jp/zenkoku/MC1",
      "name": "https://www.shigotomo.jp/zenkoku/MC1"
    },
    {
      "id": "https://www.shigotomo.jp/kyujin/search-detail",
      "name": "https://www.shigotomo.jp/kyujin/search-detail"
    }
  ],
  "links": [
    {
      "source": "会社見学 服装 女性",
      "target": "https://www.shigotomo.jp/contents/articles/interview-clothes",
      "value": 7,
      "tooltip": "会社見学 服装 女性 > /contents/articles/interview-clothes"
    },
    {
      "source": "https://www.shigotomo.jp/contents/articles/interview-clothes",
      "target": "https://www.shigotomo.jp/zenkoku/MC1",
      "value": 1.47,
      "tooltip": "会社見学 服装 女性 > /contents/articles/interview-clothes > /zenkoku/MC1"
    },
    {
      "source": "https://www.shigotomo.jp/zenkoku/MC1",
      "target": "https://www.shigotomo.jp/kyujin/search-detail",
      "value": 0.59,
      "tooltip": "会社見学 服装 女性 > /contents/articles/interview-clothes > /zenkoku/MC1 > /kyujin/search-detail"
    }
  ]
}