{
  "nodes": [
    {
      "id": "倉庫内作業 きつい",
      "name": "倉庫内作業 きつい"
    },
    {
      "id": "https://www.shigotomo.jp/contents/articles/keisagyo-haken-hard",
      "name": "https://www.shigotomo.jp/contents/articles/keisagyo-haken-hard"
    },
    {
      "id": "https://www.shigotomo.jp/zenkoku/MC1",
      "name": "https://www.shigotomo.jp/zenkoku/MC1"
    },
    {
      "id": "https://www.shigotomo.jp/apply/535",
      "name": "https://www.shigotomo.jp/apply/535"
    },
    {
      "id": "https://www.shigotomo.jp/zenkoku/MC1/EC1",
      "name": "https://www.shigotomo.jp/zenkoku/MC1/EC1"
    },
    {
      "id": "https://www.shigotomo.jp/kyujin/search-detail",
      "name": "https://www.shigotomo.jp/kyujin/search-detail"
    },
    {
      "id": "https://www.shigotomo.jp/apply/confirm",
      "name": "https://www.shigotomo.jp/apply/confirm"
    }
  ],
  "links": [
    {
      "source": "倉庫内作業 きつい",
      "target": "https://www.shigotomo.jp/contents/articles/keisagyo-haken-hard",
      "value": 19,
      "tooltip": "倉庫内作業 きつい > /contents/articles/keisagyo-haken-hard"
    },
    {
      "source": "https://www.shigotomo.jp/contents/articles/keisagyo-haken-hard",
      "target": "https://www.shigotomo.jp/zenkoku/MC1",
      "value": 1.76,
      "tooltip": "倉庫内作業 きつい > /contents/articles/keisagyo-haken-hard > /zenkoku/MC1"
    },
    {
      "source": "https://www.shigotomo.jp/contents/articles/keisagyo-haken-hard",
      "target": "https://www.shigotomo.jp/apply/535",
      "value": 0.59,
      "tooltip": "倉庫内作業 きつい > /contents/articles/keisagyo-haken-hard > /apply/535"
    },
    {
      "source": "https://www.shigotomo.jp/contents/articles/keisagyo-haken-hard",
      "target": "https://www.shigotomo.jp/zenkoku/MC1/EC1",
      "value": 5.09,
      "tooltip": "倉庫内作業 きつい > /contents/articles/keisagyo-haken-hard > /zenkoku/MC1/EC1"
    },
    {
      "source": "https://www.shigotomo.jp/zenkoku/MC1",
      "target": "https://www.shigotomo.jp/kyujin/search-detail",
      "value": 0.71,
      "tooltip": "倉庫内作業 きつい > /contents/articles/keisagyo-haken-hard > /zenkoku/MC1 > /kyujin/search-detail"
    },
    {
      "source": "https://www.shigotomo.jp/zenkoku/MC1/EC1",
      "target": "https://www.shigotomo.jp/kyujin/search-detail",
      "value": 1.08,
      "tooltip": "倉庫内作業 きつい > /contents/articles/keisagyo-haken-hard > /zenkoku/MC1/EC1 > /kyujin/search-detail"
    },
    {
      "source": "https://www.shigotomo.jp/apply/535",
      "target": "https://www.shigotomo.jp/apply/confirm",
      "value": 0.59,
      "tooltip": "倉庫内作業 きつい > /contents/articles/keisagyo-haken-hard > /apply/535 > /apply/confirm"
    }
  ]
}