{
  "nodes": [
    {
      "id": "工場 面接 落ちる",
      "name": "工場 面接 落ちる"
    },
    {
      "id": "https://www.shigotomo.jp/contents/articles/koujohaken-daredemo-ukaru",
      "name": "https://www.shigotomo.jp/contents/articles/koujohaken-daredemo-ukaru"
    },
    {
      "id": "https://www.shigotomo.jp/zenkoku/PC27/FW工場　派遣",
      "name": "https://www.shigotomo.jp/zenkoku/PC27/FW工場　派遣"
    },
    {
      "id": "https://www.shigotomo.jp/kyujin/search-detail",
      "name": "https://www.shigotomo.jp/kyujin/search-detail"
    }
  ],
  "links": [
    {
      "source": "工場 面接 落ちる",
      "target": "https://www.shigotomo.jp/contents/articles/koujohaken-daredemo-ukaru",
      "value": 4,
      "tooltip": "工場 面接 落ちる > /contents/articles/koujohaken-daredemo-ukaru"
    },
    {
      "source": "https://www.shigotomo.jp/contents/articles/koujohaken-daredemo-ukaru",
      "target": "https://www.shigotomo.jp/zenkoku/PC27/FW工場　派遣",
      "value": 2.18,
      "tooltip": "工場 面接 落ちる > /contents/articles/koujohaken-daredemo-ukaru > /zenkoku/PC27/FW工場　派遣"
    },
    {
      "source": "https://www.shigotomo.jp/zenkoku/PC27/FW工場　派遣",
      "target": "https://www.shigotomo.jp/kyujin/search-detail",
      "value": 0.73,
      "tooltip": "工場 面接 落ちる > /contents/articles/koujohaken-daredemo-ukaru > /zenkoku/PC27/FW工場　派遣 > /kyujin/search-detail"
    }
  ]
}