{
  "nodes": [
    {
      "id": "派遣 飛ぶ",
      "name": "派遣 飛ぶ"
    },
    {
      "id": "https://www.shigotomo.jp/contents/articles/koujohaken-bakkure-taisho",
      "name": "https://www.shigotomo.jp/contents/articles/koujohaken-bakkure-taisho"
    },
    {
      "id": "https://www.shigotomo.jp/apply/535",
      "name": "https://www.shigotomo.jp/apply/535"
    },
    {
      "id": "https://www.shigotomo.jp/zenkoku/EC1/FW工場",
      "name": "https://www.shigotomo.jp/zenkoku/EC1/FW工場"
    },
    {
      "id": "https://www.shigotomo.jp/apply/confirm",
      "name": "https://www.shigotomo.jp/apply/confirm"
    }
  ],
  "links": [
    {
      "source": "派遣 飛ぶ",
      "target": "https://www.shigotomo.jp/contents/articles/koujohaken-bakkure-taisho",
      "value": 3,
      "tooltip": "派遣 飛ぶ > /contents/articles/koujohaken-bakkure-taisho"
    },
    {
      "source": "https://www.shigotomo.jp/contents/articles/koujohaken-bakkure-taisho",
      "target": "https://www.shigotomo.jp/apply/535",
      "value": 0.5,
      "tooltip": "派遣 飛ぶ > /contents/articles/koujohaken-bakkure-taisho > /apply/535"
    },
    {
      "source": "https://www.shigotomo.jp/contents/articles/koujohaken-bakkure-taisho",
      "target": "https://www.shigotomo.jp/zenkoku/EC1/FW工場",
      "value": 1.5,
      "tooltip": "派遣 飛ぶ > /contents/articles/koujohaken-bakkure-taisho > /zenkoku/EC1/FW工場"
    },
    {
      "source": "https://www.shigotomo.jp/apply/535",
      "target": "https://www.shigotomo.jp/apply/confirm",
      "value": 0.5,
      "tooltip": "派遣 飛ぶ > /contents/articles/koujohaken-bakkure-taisho > /apply/535 > /apply/confirm"
    }
  ]
}