{
  "nodes": [
    {
      "id": "職場見学 服装 派遣",
      "name": "職場見学 服装 派遣"
    },
    {
      "id": "https://www.shigotomo.jp/contents/articles/interview-clothes",
      "name": "https://www.shigotomo.jp/contents/articles/interview-clothes"
    },
    {
      "id": "https://www.shigotomo.jp/zenkoku/MC1",
      "name": "https://www.shigotomo.jp/zenkoku/MC1"
    },
    {
      "id": "https://www.shigotomo.jp/kyujin/search-detail",
      "name": "https://www.shigotomo.jp/kyujin/search-detail"
    }
  ],
  "links": [
    {
      "source": "職場見学 服装 派遣",
      "target": "https://www.shigotomo.jp/contents/articles/interview-clothes",
      "value": 9,
      "tooltip": "職場見学 服装 派遣 > /contents/articles/interview-clothes"
    },
    {
      "source": "https://www.shigotomo.jp/contents/articles/interview-clothes",
      "target": "https://www.shigotomo.jp/zenkoku/MC1",
      "value": 1.89,
      "tooltip": "職場見学 服装 派遣 > /contents/articles/interview-clothes > /zenkoku/MC1"
    },
    {
      "source": "https://www.shigotomo.jp/zenkoku/MC1",
      "target": "https://www.shigotomo.jp/kyujin/search-detail",
      "value": 0.76,
      "tooltip": "職場見学 服装 派遣 > /contents/articles/interview-clothes > /zenkoku/MC1 > /kyujin/search-detail"
    }
  ]
}