{
  "nodes": [
    {
      "id": "職場見学 服装 オフィスカジュアル",
      "name": "職場見学 服装 オフィスカジュアル"
    },
    {
      "id": "https://www.shigotomo.jp/contents/articles/interview-clothes",
      "name": "https://www.shigotomo.jp/contents/articles/interview-clothes"
    },
    {
      "id": "https://www.shigotomo.jp/zenkoku/MC1",
      "name": "https://www.shigotomo.jp/zenkoku/MC1"
    },
    {
      "id": "https://www.shigotomo.jp/zenkoku/EC1/FW工場",
      "name": "https://www.shigotomo.jp/zenkoku/EC1/FW工場"
    },
    {
      "id": "https://www.shigotomo.jp/kyujin/search-detail",
      "name": "https://www.shigotomo.jp/kyujin/search-detail"
    }
  ],
  "links": [
    {
      "source": "職場見学 服装 オフィスカジュアル",
      "target": "https://www.shigotomo.jp/contents/articles/interview-clothes",
      "value": 13,
      "tooltip": "職場見学 服装 オフィスカジュアル > /contents/articles/interview-clothes"
    },
    {
      "source": "https://www.shigotomo.jp/contents/articles/interview-clothes",
      "target": "https://www.shigotomo.jp/zenkoku/MC1",
      "value": 2.74,
      "tooltip": "職場見学 服装 オフィスカジュアル > /contents/articles/interview-clothes > /zenkoku/MC1"
    },
    {
      "source": "https://www.shigotomo.jp/contents/articles/interview-clothes",
      "target": "https://www.shigotomo.jp/zenkoku/EC1/FW工場",
      "value": 0.68,
      "tooltip": "職場見学 服装 オフィスカジュアル > /contents/articles/interview-clothes > /zenkoku/EC1/FW工場"
    },
    {
      "source": "https://www.shigotomo.jp/zenkoku/MC1",
      "target": "https://www.shigotomo.jp/kyujin/search-detail",
      "value": 1.09,
      "tooltip": "職場見学 服装 オフィスカジュアル > /contents/articles/interview-clothes > /zenkoku/MC1 > /kyujin/search-detail"
    }
  ]
}